cgn_ec_models/enums.py
cgn_ec_models/sqlmodel.py
cgn_ec_models-0.4.0.dist-info/LICENSE
cgn_ec_models-0.4.0.dist-info/METADATA
cgn_ec_models-0.4.0.dist-info/WHEEL
cgn_ec_models-0.4.0.dist-info/RECORD
