Metadata-Version: 2.3
Name: cgn-ec-models
Version: 0.4.0
Summary: Models for cgn-ec
Author: BSpendlove
Author-email: 8687668+BSpendlove@users.noreply.github.com
Requires-Python: >=3.12,<4.0
Classifier: Programming Language :: Python :: 3
Classifier: Programming Language :: Python :: 3.12
Classifier: Programming Language :: Python :: 3.13
Requires-Dist: pydantic (>=2.10.6,<3.0.0)
Requires-Dist: sqlmodel (>=0.0.24,<0.0.25)
